git_clone/__init__.py
git_clone/git_clone.py
project_setup/__init__.py
project_setup/project_setup.py
ai_project_setup-0.2.8.dist-info/METADATA
ai_project_setup-0.2.8.dist-info/WHEEL
ai_project_setup-0.2.8.dist-info/top_level.txt
ai_project_setup-0.2.8.dist-info/RECORD
