Metadata-Version: 2.1
Name: ai_project_setup
Version: 0.2.8
Summary: A versatile utility package designed to streamline the setup of AI project structures while seamlessly integrating with Git repositories and Google Colab, simplifying the process of building collaborative AI projects.
Author: Patrick Ogbuitepu
Author-email: pat2echo@gmail.com
Keywords: AI,utility package,project structure,Git integration,Google Colab integration,collaborative projects,ease of use,streamlined workflow,automation,project management,project,setup,structure,ai,artificial intelligence,research,data science,machine learning
